pyvoy/__init__.py
pyvoy/_bin/__init__.py
pyvoy/_bin/libpyvoy.so
pyvoy/_cli.py
pyvoy/_debug.py
pyvoy/_server.py
pyvoy/_watcher.py
pyvoy/py.typed
pyvoy-0.3.0.dist-info/licenses/LICENSE
pyvoy-0.3.0.dist-info/WHEEL
pyvoy-0.3.0.dist-info/entry_points.txt
pyvoy-0.3.0.dist-info/METADATA
pyvoy-0.3.0.dist-info/RECORD
