Metadata-Version: 2.4
Name: pyvoy
Version: 0.3.0
Summary: A Python app server based on envoy
Keywords: asgi,envoy,wsgi
Author: CurioSwitch
License-File: LICENSE
Classifier: Development Status :: 4 - Beta
Classifier: Intended Audience :: Developers
Classifier: License :: OSI Approved :: MIT License
Classifier: Operating System :: MacOS :: MacOS X
Classifier: Operating System :: POSIX :: Linux
Classifier: Programming Language :: Python
Classifier: Programming Language :: Python :: 3
Classifier: Programming Language :: Python :: 3.10
Classifier: Programming Language :: Python :: 3.11
Classifier: Programming Language :: Python :: 3.12
Classifier: Programming Language :: Python :: 3.13
Classifier: Programming Language :: Python :: 3.14
Classifier: Programming Language :: Python :: Implementation :: CPython
Classifier: Programming Language :: Rust
Classifier: Topic :: Internet :: WWW/HTTP
Classifier: Topic :: Internet :: WWW/HTTP :: WSGI :: Server
Requires-Dist: envoy-server==1.37.0
Requires-Dist: find-libpython
Requires-Dist: pyyaml
Requires-Dist: uvloop ; sys_platform != 'win32'
Requires-Dist: winloop ; sys_platform == 'win32'
Requires-Python: >=3.10
Project-URL: Changelog, https://github.com/curioswitch/pyvoy/releases
Project-URL: Homepage, https://github.com/curioswitch/pyvoy
Project-URL: Issues, https://github.com/curioswitch/pyvoy/issues
Project-URL: Repository, https://github.com/curioswitch/pyvoy.git
